{
  "classic-tiramisu": {
    "name": "經典提拉米蘇",
    "price": "NT$290 起",
    "originalPrice": "NT$390",
    "description": "招牌！馬斯卡彭奶霜 × 現萃咖啡 × 咖啡酒，濃香不膩",
    "image": "https://antnest-chatbot.vercel.app/images/classic-tiramisu-plated.jpeg",
    "url": "https://antnest.cyberbiz.co/products/classic-tiramisu",
    "badges": ["🏆 招牌", "🍷 含酒精"]
  },
  "oreo-tiramisu": {
    "name": "極濃奧利奧提拉米蘇",
    "price": "NT$300",
    "originalPrice": "NT$400",
    "description": "以牛奶取代咖啡與酒，奧利奧控最愛！大人小孩都適合",
    "image": "https://antnest-chatbot.vercel.app/images/oreo-tiramisu-with-box.jpeg",
    "url": "https://antnest.cyberbiz.co/products/oreo-tiramisu",
    "badges": ["✅ 無酒精", "🌱 蛋奶素"]
  },
  "super-crispy-tiramisu": {
    "name": "超級脆脆提拉米蘇",
    "price": "NT$379 起",
    "originalPrice": "NT$499",
    "description": "杜拜巧克力延伸系列！雙層結構，脆脆層 × 馬斯卡彭奶霜",
    "image": "https://antnest-chatbot.vercel.app/images/classic-tiramisu-with-box.jpeg",
    "url": "https://antnest.cyberbiz.co/products/black-chocolate-tiramisu",
    "badges": ["✅ 無酒精", "🔥 人氣"]
  },
  "luxe-cheesecake": {
    "name": "北海道 LUXE 巴斯克",
    "price": "NT$370 起",
    "originalPrice": null,
    "description": "北海道頂級奶油乳酪，減糖配方，不愛甜的人首選",
    "image": "https://antnest-chatbot.vercel.app/images/luxe-cheesecake-side.jpeg",
    "url": "https://antnest.cyberbiz.co/products/luxe-cheesecake",
    "badges": ["✅ 無酒精", "🧀 減糖"]
  },
  "legall-cheesecake": {
    "name": "法國 Le Gall 重乳酪",
    "price": "NT$99",
    "originalPrice": null,
    "description": "螞蟻窩的起點！法國百年品牌乳酪，三層結構，濃郁不膩",
    "image": "https://antnest-chatbot.vercel.app/images/plain-cheesecake-full.jpeg",
    "url": "https://antnest.cyberbiz.co/products/legall-cheesecake",
    "badges": ["✅ 無酒精", "💰 超值"]
  },
  "canele": {
    "name": "法式經典可麗露",
    "price": "NT$70",
    "originalPrice": null,
    "description": "外酥內軟，焦糖與香草完美平衡，越嚼越香",
    "image": "https://antnest-chatbot.vercel.app/images/canele-whole.jpeg",
    "url": "https://antnest.cyberbiz.co/products/canele",
    "badges": ["✅ 無酒精", "🌱 蛋奶素"]
  },
  "snowflake-cookies": {
    "name": "經典口袋雪Q餅",
    "price": "NT$150 起",
    "originalPrice": null,
    "description": "回購率最高！半天賣出 1,200 包，三種口味，Q糯不黏牙",
    "image": "https://antnest-chatbot.vercel.app/images/snowflake-cookies-cubes.jpeg",
    "url": "https://antnest.cyberbiz.co/products/snowflake-cookies",
    "badges": ["✅ 無酒精", "🔥 回購王"]
  }
}
